{"frameRate":24,"name":"RedBlueBlock","version":"5.5","compatibleVersion":"5.5","armature":[{"type":"Armature","frameRate":24,"name":"Armature","aabb":{"x":-317.95,"y":-320,"width":640,"height":640},"bone":[{"name":"root"},{"length":319,"name":"new","parent":"root","transform":{"x":2.05,"skX":-90,"skY":-90}}],"slot":[{"name":"block","parent":"new"}],"skin":[{"slot":[{"name":"block","display":[{"name":"block","transform":{"skX":90,"skY":90}}]}]}],"animation":[{"duration":0,"playTimes":0,"name":"Init"},{"duration":8,"playTimes":0,"name":"Hit","bone":[{"name":"root","translateFrame":[{"duration":2,"curve":[0,0,0.20929024390243903,-0.03262265861027186,0.42007624390243903,0.17816334138972814,0.6994902439024391,0.45757734138972816,0.7170731707317073,0.9909365558912386],"y":-4.29},{"duration":6,"curve":[0,0,0.20929024390243903,-0.03262265861027186,0.42007624390243903,0.17816334138972814,0.6994902439024391,0.45757734138972816,0.7170731707317073,0.9909365558912386],"y":-324.43},{"duration":0,"y":-4.77}],"scaleFrame":[{"duration":2,"tweenEasing":0},{"duration":6,"tweenEasing":0,"x":1.11,"y":1.11},{"duration":0,"x":0.97,"y":0.97}]},{"name":"new","translateFrame":[{"duration":8,"x":-2.05}],"scaleFrame":[{"duration":2,"tweenEasing":0},{"duration":6,"tweenEasing":0,"x":1.11,"y":1.11},{"duration":0}]}]},{"duration":0,"playTimes":0,"name":"edit_default"},{"duration":4,"playTimes":0,"name":"edit_select","bone":[{"name":"new","translateFrame":[{"duration":4,"x":-2.05}],"scaleFrame":[{"duration":4,"tweenEasing":0},{"duration":0,"x":1.25,"y":1.25}]}]},{"duration":4,"playTimes":0,"name":"edit_deselect","bone":[{"name":"new","translateFrame":[{"duration":4,"x":-2.05}],"scaleFrame":[{"duration":4,"tweenEasing":0,"x":1.25,"y":1.25},{"duration":0}]}]}],"defaultActions":[{"gotoAndPlay":"Init"}]}]}